trafficLight.v
module traffic_light_controller (
    input clk,           // to manipulate the timing of trafic light
    input reset,         // will reset the controller to base state (eyat red loisu)
    output reg red,      // RED light control signal
    output reg yellow,   // YELLOW light control signal
    output reg green     // GREEN light control signal
);

    // each state has been considered as a 2 bit binary- 00, 01, 10 (11 can be imagined as don't care in this case)
    parameter GREEN = 2'b00, 
              YELLOW = 2'b01, 
              RED = 2'b10;

    // current state and the next state of the traffic light
    reg [1:0] state, next_state;

    // timer to keep track of how long we’ve been in the current state
    reg [3:0] timer;

    // [x:0]: x bits in total. i.e. 0000 to 2^x - 1 (in binary)

    // this block runs on every rising edge of the clock or when reset is triggered
    always @(posedge clk or posedge reset) begin
        if (reset) begin
            // reset hole RED state ole gusi jua and reset the timer
            state <= RED;
            timer <= 0;
        end 
        else begin
            // updating the state to the next state
            state <= next_state;

            // timer will count up to a max value depending on the state
            // for GREEN and RED, it goes to 9 (i.e., 10 cycles)
            // for yellow, it goes to 4 (i.e., 5 cycles)
            if (timer == 4'd9)
                timer <= 0;
            else
                timer <= timer + 1;
        end
    end

    // combinational logic to decide what is next state
    // and which light (RED, YELLOW, GREEN) should be on
    always @(*) begin
        // by default all off
        red = 0;
        yellow = 0;
        green = 0;

        // setting lights and next state based on current state and timer
        // this is a switch case code
        case (state)
            GREEN: begin
                green = 1; // Turn on GREEN light
                // after 10 clock cycles in GREEN, switch to YELLOW
                next_state = (timer == 4'd9) ? YELLOW : GREEN;
            end

            YELLOW: begin
                yellow = 1; // Turn on YELLOW light
                // after 5 clock cycles in YELLOW, switch to RED
                next_state = (timer == 4'd4) ? RED : YELLOW;
            end

            RED: begin
                red = 1; // Turn on RED light
                // after 10 clock cycles in RED, switch to GREEN
                next_state = (timer == 4'd9) ? GREEN : RED;
            end

            default: begin
                // safety net: in case of undefined input, go to RED
                next_state = RED;
            end
        endcase
    end

endmodule

trafficLightTB.v
// testbench for the traffic_light_controller module
`timescale 1ns / 1ps // set time unit to 1 ns and time precision to 1 ps

module tb_traffic_light;

    // declaring signals to connect to the traffic light controller
    reg clk;             // clock signal
    reg reset;           // reset signal
    wire red, yellow, green; // outputs from the module (leds)

    // instantiating the unit under test (uut)
    traffic_light_controller uut (
        .clk(clk),
        .reset(reset),
        .red(red),
        .yellow(yellow),
        .green(green)
    );

    // this initial block runs once at the beginning of simulation
    initial begin
        // print a header for readability
        $display("time\tred\tyellow\tgreen");

        // continuously monitor and print the output values during simulation
        $monitor("%0t\t%b\t%b\t%b", $time, red, yellow, green);

        // dumping waveform data to a .vcd file (for gtkwave simulation)
        $dumpfile("traffic_light.vcd");         // name of output vcd file
        $dumpvars(0, tb_traffic_light);         // record all variables in this module

        // initialising clock and reset
        clk = 0;        // start clock at 0
        reset = 1;      // activate reset to initialize the system
        #5 reset = 0;   // after 5 time units, deactivate reset
    end

    // clock generation: toggle clk every 5 time units (10 units total = 1 full clock cycle)
    always #5 clk = ~clk;

    // automatically stop the simulation after 200 time units
    initial begin
        #200 $finish;
    end

endmodule

traffic_light.vcd
$date
	Tue Jun 10 01:22:27 2025
$end
$version
	Icarus Verilog
$end
$timescale
	1ps
$end
$scope module tb_traffic_light $end
$var wire 1 ! green $end
$var wire 1 " red $end
$var wire 1 # yellow $end
$var reg 1 $ clk $end
$var reg 1 % reset $end
$scope module uut $end
$var wire 1 & clk $end
$var wire 1 ' reset $end
$var reg 1 ( green $end
$var reg 2 ) next_state [1:0] $end
$var reg 1 * red $end
$var reg 2 + state [1:0] $end
$var reg 4 , timer [3:0] $end
$var reg 1 - yellow $end
$upscope $end
$upscope $end
$enddefinitions $end
#0
$dumpvars
0-
b0 ,
b10 +
1*
b10 )
0(
1'
0&
1%
0$
0#
1"
0!
$end
#5000
1*
1"
b1 ,
1$
1&
0%
0'
#10000
0$
0&
#15000
1*
1"
b10 ,
1$
1&
#20000
0$
0&
#25000
1*
1"
b11 ,
1$
1&
#30000
0$
0&
#35000
1*
1"
b100 ,
1$
1&
#40000
0$
0&
#45000
1*
1"
b101 ,
1$
1&
#50000
0$
0&
#55000
1*
1"
b110 ,
1$
1&
#60000
0$
0&
#65000
1*
1"
b111 ,
1$
1&
#70000
0$
0&
#75000
1*
1"
b1000 ,
1$
1&
#80000
0$
0&
#85000
b0 )
1*
1"
b1001 ,
1$
1&
#90000
0$
0&
#95000
1(
1!
0*
0"
b0 ,
b0 +
1$
1&
#100000
0$
0&
#105000
1(
1!
b1 ,
1$
1&
#110000
0$
0&
#115000
1(
1!
b10 ,
1$
1&
#120000
0$
0&
#125000
1(
1!
b11 ,
1$
1&
#130000
0$
0&
#135000
1(
1!
b100 ,
1$
1&
#140000
0$
0&
#145000
1(
1!
b101 ,
1$
1&
#150000
0$
0&
#155000
1(
1!
b110 ,
1$
1&
#160000
0$
0&
#165000
1(
1!
b111 ,
1$
1&
#170000
0$
0&
#175000
1(
1!
b1000 ,
1$
1&
#180000
0$
0&
#185000
b1 )
1(
1!
b1001 ,
1$
1&
#190000
0$
0&
#195000
1-
1#
0(
0!
b0 ,
b1 +
1$
1&
